git_cache_clone/__init__.py
git_cache_clone/cli/__init__.py
git_cache_clone/cli/arguments.py
git_cache_clone/cli/commands/__init__.py
git_cache_clone/cli/commands/add.py
git_cache_clone/cli/commands/clean.py
git_cache_clone/cli/commands/clone.py
git_cache_clone/cli/commands/info.py
git_cache_clone/cli/commands/refresh.py
git_cache_clone/cli/main.py
git_cache_clone/cli/utils.py
git_cache_clone/config.py
git_cache_clone/constants/__init__.py
git_cache_clone/constants/core.py
git_cache_clone/constants/defaults.py
git_cache_clone/constants/filenames.py
git_cache_clone/constants/keys.py
git_cache_clone/core.py
git_cache_clone/errors.py
git_cache_clone/metadata/__init__.py
git_cache_clone/metadata/collection.py
git_cache_clone/metadata/json_store/__init__.py
git_cache_clone/metadata/json_store/applier_and_fetcher.py
git_cache_clone/metadata/lock.py
git_cache_clone/metadata/memory_store/__init__.py
git_cache_clone/metadata/memory_store/applier_and_fetcher.py
git_cache_clone/metadata/protocols.py
git_cache_clone/metadata/repo.py
git_cache_clone/metadata/sqlite_store/__init__.py
git_cache_clone/metadata/sqlite_store/adapters_converters.py
git_cache_clone/metadata/sqlite_store/applier_and_fetcher.py
git_cache_clone/metadata/sqlite_store/db.py
git_cache_clone/metadata/sqlite_store/repo.py
git_cache_clone/metadata/utils.py
git_cache_clone/pod/__init__.py
git_cache_clone/pod/pod.py
git_cache_clone/result.py
git_cache_clone/types.py
git_cache_clone/utils/__init__.py
git_cache_clone/utils/file_lock.py
git_cache_clone/utils/git.py
git_cache_clone/utils/logging.py
git_cache_clone/utils/misc.py
git_cache_clone-0.2.0.dist-info/LICENSE
git_cache_clone-0.2.0.dist-info/METADATA
git_cache_clone-0.2.0.dist-info/WHEEL
git_cache_clone-0.2.0.dist-info/entry_points.txt
git_cache_clone-0.2.0.dist-info/RECORD
